{
  "metadata": {
    "generated_at": "2024-12-19T10:30:00Z",
    "source_file": "metadata/metadata.json",
    "description": "Supply Chain Graph Data Model extracted from 15 CSV files",
    "total_nodes": 150,
    "total_edges": 150
  },
  "nodes": [
    {"id": "CR900", "attributes": {"name": "Carrier_0", "type": "Carrier", "service_level": "Express", "phone": "+91-880002000"}},
    {"id": "CR901", "attributes": {"name": "Carrier_1", "type": "Carrier", "service_level": "Standard", "phone": "+91-880002001"}},
    {"id": "CR902", "attributes": {"name": "Carrier_2", "type": "Carrier", "service_level": "Standard", "phone": "+91-880002002"}},
    {"id": "C500", "attributes": {"name": "Customer_0", "type": "Customer", "segment": "Retail", "city": "Delhi", "contact_email": "cust0@example.com"}},
    {"id": "C501", "attributes": {"name": "Customer_1", "type": "Customer", "segment": "Retail", "city": "Mumbai", "contact_email": "cust1@example.com"}},
    {"id": "C502", "attributes": {"name": "Customer_2", "type": "Customer", "segment": "Wholesale", "city": "Chennai", "contact_email": "cust2@example.com"}},
    {"id": "C506", "attributes": {"name": "Customer_6", "type": "Customer", "segment": "Corporate", "city": "Bangalore", "contact_email": "cust6@example.com"}},
    {"id": "C508", "attributes": {"name": "Customer_8", "type": "Customer", "segment": "Retail", "city": "Pune", "contact_email": "cust8@example.com"}},
    {"id": "I400", "attributes": {"type": "Inventory", "quantity_on_hand": 93, "reorder_point": 95, "last_updated": "2025-01-01"}},
    {"id": "I401", "attributes": {"type": "Inventory", "quantity_on_hand": 179, "reorder_point": 27, "last_updated": "2025-01-02"}},
    {"id": "I402", "attributes": {"type": "Inventory", "quantity_on_hand": 25, "reorder_point": 139, "last_updated": "2025-01-03"}},
    {"id": "INV1200", "attributes": {"type": "Invoice", "invoice_date": "2025-01-03", "amount_due": 16591.76, "status": "Unpaid"}},
    {"id": "INV1201", "attributes": {"type": "Invoice", "invoice_date": "2025-01-04", "amount_due": 4861.66, "status": "Paid"}},
    {"id": "INV1202", "attributes": {"type": "Invoice", "invoice_date": "2025-01-05", "amount_due": 12437.05, "status": "Paid"}},
    {"id": "INV1206", "attributes": {"type": "Invoice", "invoice_date": "2025-01-06", "amount_due": 13279.83, "status": "Paid"}},
    {"id": "INV1208", "attributes": {"type": "Invoice", "invoice_date": "2025-01-08", "amount_due": 13279.83, "status": "Paid"}},
    {"id": "E1500", "attributes": {"type": "LogisticsEvent", "event_time": "2025-01-02 10:00:00", "event_type": "Picked Up", "location": "Chennai"}},
    {"id": "E1501", "attributes": {"type": "LogisticsEvent", "event_time": "2025-01-03 10:00:00", "event_type": "In Transit", "location": "Mumbai"}},
    {"id": "E1502", "attributes": {"type": "LogisticsEvent", "event_time": "2025-01-04 10:00:00", "event_type": "Delayed", "location": "Delhi"}},
    {"id": "OI700", "attributes": {"type": "OrderItem", "quantity": 2, "unit_price": 1886.05}},
    {"id": "OI701", "attributes": {"type": "OrderItem", "quantity": 7, "unit_price": 603.45}},
    {"id": "OI702", "attributes": {"type": "OrderItem", "quantity": 1, "unit_price": 2233.47}},
    {"id": "O600", "attributes": {"type": "Order", "order_date": "2025-01-01", "status": "Pending", "total_amount": 7080.71}},
    {"id": "O601", "attributes": {"type": "Order", "order_date": "2025-01-02", "status": "Shipped", "total_amount": 12017.72}},
    {"id": "O602", "attributes": {"type": "Order", "order_date": "2025-01-03", "status": "Delivered", "total_amount": 14856.57}},
    {"id": "O603", "attributes": {"type": "Order", "order_date": "2025-01-04", "status": "Cancelled", "total_amount": 12437.05}},
    {"id": "O606", "attributes": {"type": "Order", "order_date": "2025-01-07", "status": "Processing", "total_amount": 2233.47}},
    {"id": "O608", "attributes": {"type": "Order", "order_date": "2025-01-09", "status": "Pending", "total_amount": 16591.76}},
    {"id": "O609", "attributes": {"type": "Order", "order_date": "2025-01-10", "status": "Shipped", "total_amount": 3772.10}},
    {"id": "PMT1300", "attributes": {"type": "Payment", "payment_date": "2025-01-04", "amount_paid": 13279.83, "method": "Bank Transfer"}},
    {"id": "PMT1301", "attributes": {"type": "Payment", "payment_date": "2025-01-05", "amount_paid": 4861.66, "method": "Card"}},
    {"id": "PMT1302", "attributes": {"type": "Payment", "payment_date": "2025-01-06", "amount_paid": 13279.83, "method": "Card"}},
    {"id": "P200", "attributes": {"name": "Product_0", "type": "Product", "sku": "SKU-3000", "category": "Electronics", "unit_weight_kg": 0.5}},
    {"id": "P201", "attributes": {"name": "Product_1", "type": "Product", "sku": "SKU-3001", "category": "Apparel", "unit_weight_kg": 0.2}},
    {"id": "P202", "attributes": {"name": "Product_2", "type": "Product", "sku": "SKU-3002", "category": "Electronics", "unit_weight_kg": 1.2}},
    {"id": "P205", "attributes": {"name": "Product_5", "type": "Product", "sku": "SKU-3005", "category": "Home", "unit_weight_kg": 0.8}},
    {"id": "P206", "attributes": {"name": "Product_6", "type": "Product", "sku": "SKU-3006", "category": "Automotive", "unit_weight_kg": 2.1}},
    {"id": "P207", "attributes": {"name": "Product_7", "type": "Product", "sku": "SKU-3007", "category": "Toys", "unit_weight_kg": 0.3}},
    {"id": "P209", "attributes": {"name": "Product_9", "type": "Product", "sku": "SKU-3009", "category": "Electronics", "unit_weight_kg": 1.5}},
    {"id": "PO1000", "attributes": {"type": "PurchaseOrder", "order_date": "2025-01-01", "expected_delivery": "2025-01-16", "status": "Open", "total_value": 229945.04}},
    {"id": "PO1001", "attributes": {"type": "PurchaseOrder", "order_date": "2025-01-02", "expected_delivery": "2025-01-17", "status": "Closed", "total_value": 60861.29}},
    {"id": "PO1002", "attributes": {"type": "PurchaseOrder", "order_date": "2025-01-03", "expected_delivery": "2025-01-18", "status": "Open", "total_value": 484852.13}},
    {"id": "PO1008", "attributes": {"type": "PurchaseOrder", "order_date": "2025-01-09", "expected_delivery": "2025-01-24", "status": "Open", "total_value": 125000.00}},
    {"id": "R1100", "attributes": {"type": "Receipt", "quantity_received": 97, "received_date": "2025-01-06"}},
    {"id": "R1101", "attributes": {"type": "Receipt", "quantity_received": 36, "received_date": "2025-01-07"}},
    {"id": "R1102", "attributes": {"type": "Receipt", "quantity_received": 9, "received_date": "2025-01-08"}},
    {"id": "RT1400", "attributes": {"type": "Route", "destination_city": "Delhi", "distance_km": 547, "estimated_time_hours": 51.2}},
    {"id": "RT1401", "attributes": {"type": "Route", "destination_city": "Mumbai", "distance_km": 1379, "estimated_time_hours": 19.3}},
    {"id": "RT1402", "attributes": {"type": "Route", "destination_city": "Chennai", "distance_km": 1495, "estimated_time_hours": 67.0}},
    {"id": "SH800", "attributes": {"type": "Shipment", "shipped_date": "2025-01-02", "estimated_arrival": "2025-01-05"}},
    {"id": "SH801", "attributes": {"type": "Shipment", "shipped_date": "2025-01-03", "estimated_arrival": "2025-01-06"}},
    {"id": "SH802", "attributes": {"type": "Shipment", "shipped_date": "2025-01-04", "estimated_arrival": "2025-01-07"}},
    {"id": "SH804", "attributes": {"type": "Shipment", "shipped_date": "2025-01-06", "estimated_arrival": "2025-01-09"}},
    {"id": "SH806", "attributes": {"type": "Shipment", "shipped_date": "2025-01-08", "estimated_arrival": "2025-01-11"}},
    {"id": "S100", "attributes": {"name": "Supplier_0", "type": "Supplier", "country": "India", "contact_email": "supp0@example.com", "phone": "+91-900001000", "lead_time_days": 7}},
    {"id": "S101", "attributes": {"name": "Supplier_1", "type": "Supplier", "country": "China", "contact_email": "supp1@example.com", "phone": "+91-900001001", "lead_time_days": 14}},
    {"id": "S102", "attributes": {"name": "Supplier_2", "type": "Supplier", "country": "Germany", "contact_email": "supp2@example.com", "phone": "+91-900001002", "lead_time_days": 10}},
    {"id": "S104", "attributes": {"name": "Supplier_4", "type": "Supplier", "country": "USA", "contact_email": "supp4@example.com", "phone": "+91-900001004", "lead_time_days": 21}},
    {"id": "S105", "attributes": {"name": "Supplier_5", "type": "Supplier", "country": "Japan", "contact_email": "supp5@example.com", "phone": "+91-900001005", "lead_time_days": 12}},
    {"id": "S107", "attributes": {"name": "Supplier_7", "type": "Supplier", "country": "South Korea", "contact_email": "supp7@example.com", "phone": "+91-900001007", "lead_time_days": 15}},
    {"id": "W10", "attributes": {"name": "WH_0", "type": "Warehouse", "location_city": "Chennai", "capacity_units": 10000}},
    {"id": "W11", "attributes": {"name": "WH_1", "type": "Warehouse", "location_city": "Hyderabad", "capacity_units": 15000}},
    {"id": "W12", "attributes": {"name": "WH_2", "type": "Warehouse", "location_city": "Bengaluru", "capacity_units": 12000}},
    {"id": "W16", "attributes": {"name": "WH_6", "type": "Warehouse", "location_city": "Mumbai", "capacity_units": 18000}},
    {"id": "W17", "attributes": {"name": "WH_7", "type": "Warehouse", "location_city": "Delhi", "capacity_units": 20000}},
    {"id": "W18", "attributes": {"name": "WH_8", "type": "Warehouse", "location_city": "Pune", "capacity_units": 14000}},
    {"id": "W19", "attributes": {"name": "WH_9", "type": "Warehouse", "location_city": "Kolkata", "capacity_units": 16000}}
  ],
  "edges": [
    {"source": "C508", "target": "O600", "attributes": {"relationship": "places_order", "order_date": "2025-01-01"}},
    {"source": "C506", "target": "O601", "attributes": {"relationship": "places_order", "order_date": "2025-01-02"}},
    {"source": "C501", "target": "O602", "attributes": {"relationship": "places_order", "order_date": "2025-01-03"}},
    {"source": "O609", "target": "OI700", "attributes": {"relationship": "contains_item", "quantity": 2}},
    {"source": "O602", "target": "OI701", "attributes": {"relationship": "contains_item", "quantity": 7}},
    {"source": "O606", "target": "OI702", "attributes": {"relationship": "contains_item", "quantity": 1}},
    {"source": "OI700", "target": "P202", "attributes": {"relationship": "orders_product", "unit_price": 1886.05}},
    {"source": "OI701", "target": "P209", "attributes": {"relationship": "orders_product", "unit_price": 603.45}},
    {"source": "OI702", "target": "P206", "attributes": {"relationship": "orders_product", "unit_price": 2233.47}},
    {"source": "P200", "target": "S104", "attributes": {"relationship": "supplied_by", "lead_time_days": 21}},
    {"source": "P201", "target": "S105", "attributes": {"relationship": "supplied_by", "lead_time_days": 12}},
    {"source": "P202", "target": "S107", "attributes": {"relationship": "supplied_by", "lead_time_days": 15}},
    {"source": "I400", "target": "W18", "attributes": {"relationship": "stored_at", "quantity_on_hand": 93}},
    {"source": "I400", "target": "P207", "attributes": {"relationship": "tracks_product", "reorder_point": 95}},
    {"source": "I401", "target": "W11", "attributes": {"relationship": "stored_at", "quantity_on_hand": 179}},
    {"source": "I401", "target": "P201", "attributes": {"relationship": "tracks_product", "reorder_point": 27}},
    {"source": "I402", "target": "W16", "attributes": {"relationship": "stored_at", "quantity_on_hand": 25}},
    {"source": "I402", "target": "P205", "attributes": {"relationship": "tracks_product", "reorder_point": 139}},
    {"source": "O608", "target": "INV1200", "attributes": {"relationship": "generates_invoice", "amount_due": 16591.76}},
    {"source": "O602", "target": "INV1201", "attributes": {"relationship": "generates_invoice", "amount_due": 4861.66}},
    {"source": "O603", "target": "INV1202", "attributes": {"relationship": "generates_invoice", "amount_due": 12437.05}},
    {"source": "INV1206", "target": "PMT1300", "attributes": {"relationship": "paid_by", "amount_paid": 13279.83, "method": "Bank Transfer"}},
    {"source": "INV1201", "target": "PMT1301", "attributes": {"relationship": "paid_by", "amount_paid": 4861.66, "method": "Card"}},
    {"source": "INV1208", "target": "PMT1302", "attributes": {"relationship": "paid_by", "amount_paid": 13279.83, "method": "Card"}},
    {"source": "SH806", "target": "E1500", "attributes": {"relationship": "has_event", "event_type": "Picked Up", "location": "Chennai"}},
    {"source": "SH801", "target": "E1501", "attributes": {"relationship": "has_event", "event_type": "In Transit", "location": "Mumbai"}},
    {"source": "SH804", "target": "E1502", "attributes": {"relationship": "has_event", "event_type": "Delayed", "location": "Delhi"}},
    {"source": "O609", "target": "SH800", "attributes": {"relationship": "shipped_via", "shipped_date": "2025-01-02"}},
    {"source": "O601", "target": "SH801", "attributes": {"relationship": "shipped_via", "shipped_date": "2025-01-03"}},
    {"source": "O602", "target": "SH802", "attributes": {"relationship": "shipped_via", "shipped_date": "2025-01-04"}},
    {"source": "SH800", "target": "CR900", "attributes": {"relationship": "handled_by_carrier", "service_level": "Express"}},
    {"source": "SH801", "target": "CR901", "attributes": {"relationship": "handled_by_carrier", "service_level": "Standard"}},
    {"source": "SH802", "target": "CR902", "attributes": {"relationship": "handled_by_carrier", "service_level": "Standard"}},
    {"source": "SH800", "target": "W17", "attributes": {"relationship": "originates_from_warehouse", "location_city": "Delhi"}},
    {"source": "SH801", "target": "W16", "attributes": {"relationship": "originates_from_warehouse", "location_city": "Mumbai"}},
    {"source": "SH802", "target": "W19", "attributes": {"relationship": "originates_from_warehouse", "location_city": "Kolkata"}},
    {"source": "PO1000", "target": "S101", "attributes": {"relationship": "ordered_from_supplier", "total_value": 229945.04, "expected_delivery": "2025-01-16"}},
    {"source": "PO1001", "target": "S100", "attributes": {"relationship": "ordered_from_supplier", "total_value": 60861.29, "expected_delivery": "2025-01-17"}},
    {"source": "PO1002", "target": "S105", "attributes": {"relationship": "ordered_from_supplier", "total_value": 484852.13, "expected_delivery": "2025-01-18"}},
    {"source": "R1100", "target": "PO1008", "attributes": {"relationship": "receives_from_po", "quantity_received": 97}},
    {"source": "R1101", "target": "PO1002", "attributes": {"relationship": "receives_from_po", "quantity_received": 36}},
    {"source": "R1102", "target": "PO1008", "attributes": {"relationship": "receives_from_po", "quantity_received": 9}},
    {"source": "R1100", "target": "P206", "attributes": {"relationship": "receives_product", "quantity_received": 97}},
    {"source": "R1101", "target": "P206", "attributes": {"relationship": "receives_product", "quantity_received": 36}},
    {"source": "R1102", "target": "P205", "attributes": {"relationship": "receives_product", "quantity_received": 9}},
    {"source": "R1100", "target": "W11", "attributes": {"relationship": "delivered_to_warehouse", "received_date": "2025-01-06"}},
    {"source": "R1101", "target": "W18", "attributes": {"relationship": "delivered_to_warehouse", "received_date": "2025-01-07"}},
    {"source": "R1102", "target": "W11", "attributes": {"relationship": "delivered_to_warehouse", "received_date": "2025-01-08"}},
    {"source": "RT1400", "target": "W19", "attributes": {"relationship": "route_from_warehouse", "distance_km": 547, "destination": "Delhi"}},
    {"source": "RT1401", "target": "W18", "attributes": {"relationship": "route_from_warehouse", "distance_km": 1379, "destination": "Mumbai"}},
    {"source": "RT1402", "target": "W16", "attributes": {"relationship": "route_from_warehouse", "distance_km": 1495, "destination": "Chennai"}}
  ]
}