{
  "nodes": [
    {
      "id": "supplier_s001",
      "label": "Supplier",
      "properties": {
        "supplier_id": "S001",
        "name": "ABC Supplies Pvt Ltd",
        "contact": "raju@abc.com",
        "rating": 4.2
      }
    },
    {
      "id": "supplier_s002",
      "label": "Supplier",
      "properties": {
        "supplier_id": "S002",
        "name": "Global Tech Traders",
        "contact": "sales@globaltech.cn",
        "rating": 3.9
      }
    },
    {
      "id": "supplier_s003",
      "label": "Supplier",
      "properties": {
        "supplier_id": "S003",
        "name": "Delta Components",
        "contact": "info@delta.de",
        "rating": 4.7
      }
    },
    {
      "id": "supplier_s004",
      "label": "Supplier",
      "properties": {
        "supplier_id": "S004",
        "name": "Rapid Parts Co",
        "contact": "support@rapidparts.com",
        "rating": 4.0
      }
    },
    {
      "id": "supplier_s005",
      "label": "Supplier",
      "properties": {
        "supplier_id": "S005",
        "name": "Oceanic Imports",
        "contact": "contact@oceanic.my",
        "rating": 3.8
      }
    },
    {
      "id": "country_india",
      "label": "Country",
      "properties": {
        "name": "India"
      }
    },
    {
      "id": "country_china",
      "label": "Country",
      "properties": {
        "name": "China"
      }
    },
    {
      "id": "country_germany",
      "label": "Country",
      "properties": {
        "name": "Germany"
      }
    },
    {
      "id": "country_usa",
      "label": "Country",
      "properties": {
        "name": "USA"
      }
    },
    {
      "id": "country_malaysia",
      "label": "Country",
      "properties": {
        "name": "Malaysia"
      }
    }
  ],
  "edges": [
    {
      "source": "supplier_s001",
      "target": "country_india",
      "type": "located_in",
      "properties": {}
    },
    {
      "source": "supplier_s002",
      "target": "country_china",
      "type": "located_in",
      "properties": {}
    },
    {
      "source": "supplier_s003",
      "target": "country_germany",
      "type": "located_in",
      "properties": {}
    },
    {
      "source": "supplier_s004",
      "target": "country_usa",
      "type": "located_in",
      "properties": {}
    },
    {
      "source": "supplier_s005",
      "target": "country_malaysia",
      "type": "located_in",
      "properties": {}
    }
  ]
}